llama_index/readers/confluence/__init__.py
llama_index/readers/confluence/base.py
llama_index/readers/confluence/event.py
llama_index/readers/confluence/html_parser.py
llama_index_readers_confluence-0.6.1.dist-info/METADATA
llama_index_readers_confluence-0.6.1.dist-info/WHEEL
llama_index_readers_confluence-0.6.1.dist-info/licenses/LICENSE
llama_index_readers_confluence-0.6.1.dist-info/RECORD
