Metadata-Version: 2.4
Name: llama-index-readers-confluence
Version: 0.6.1
Summary: llama-index readers confluence integration
Author-email: Your Name <you@example.com>
Maintainer: zywilliamli
License-Expression: MIT
License-File: LICENSE
Requires-Python: <4.0,>=3.9
Requires-Dist: atlassian-python-api<5,>=3.41.9
Requires-Dist: docx2txt<0.9,>=0.8
Requires-Dist: llama-index-core<0.15,>=0.13.0
Requires-Dist: markdownify<2.0.0,>=1.2.0
Requires-Dist: pdf2image<2,>=1.17.0
Requires-Dist: pillow>=10.2.0
Requires-Dist: pytesseract<0.4,>=0.3.10
Requires-Dist: retrying<2,>=1.3.4
Requires-Dist: svglib<1.6,>=1.5
Requires-Dist: xlrd<3,>=2.0.1
